pytubev3/__init__.py
pytubev3/__main__.py
pytubev3/pytube.py
pytubev3-1.1.1.dist-info/LICENSE
pytubev3-1.1.1.dist-info/METADATA
pytubev3-1.1.1.dist-info/WHEEL
pytubev3-1.1.1.dist-info/top_level.txt
pytubev3-1.1.1.dist-info/RECORD
