Metadata-Version: 2.1
Name: pytubev3
Version: 1.1.1
Summary: Python Wrapper of Youtube API
Home-page: https://github.com/mm-mazhar/pytubev3.git
Download-URL: https://github.com/mm-mazhar/pytubev3.git
Author: Mazhar
Author-email: mazqoty.01@gmail.com
Maintainer: Mazhar
Maintainer-email: mazqoty.01@gmail.com
License: BSD
Project-URL: Bug Tracker, https://github.com/mm-mazhar/pytubev3/issues
Keywords: Youtube API,youtube api wrapper,Python,Youtube Data API
Classifier: Intended Audience :: Developers
Classifier: License :: OSI Approved :: BSD License
Classifier: Operating System :: POSIX :: Linux
Classifier: Programming Language :: Python
Requires-Python: >=3.7
License-File: LICENSE
Requires-Dist: google-api-python-client (==2.73.0)
Requires-Dist: iteration-utilities (==0.11.0)
Requires-Dist: setuptools (==65.5.0)
